puremcp/__init__.py
puremcp/cli.py
puremcp_core-0.1.0.dist-info/METADATA
puremcp_core-0.1.0.dist-info/WHEEL
puremcp_core-0.1.0.dist-info/entry_points.txt
puremcp_core-0.1.0.dist-info/licenses/LICENSE
puremcp_core-0.1.0.dist-info/RECORD
