Metadata-Version: 2.4
Name: puremcp-core
Version: 0.1.0
Summary: Core package for puremcp - Production-ready MCP servers
Project-URL: Homepage, https://puremcp.org
Project-URL: Repository, https://github.com/puremcp/puremcp
Project-URL: Issues, https://github.com/puremcp/puremcp/issues
Author: puremcp
License: Apache-2.0
License-File: LICENSE
Keywords: ai,llm,mcp,model-context-protocol
Classifier: Development Status :: 3 - Alpha
Classifier: Intended Audience :: Developers
Classifier: License :: OSI Approved :: Apache Software License
Classifier: Programming Language :: Python :: 3
Classifier: Programming Language :: Python :: 3.10
Classifier: Programming Language :: Python :: 3.11
Classifier: Programming Language :: Python :: 3.12
Classifier: Programming Language :: Python :: 3.13
Requires-Python: >=3.10
